pvnhxgmgiq/__init__.py
pvnhxgmgiq/__main__.py
pvnhxgmgiq-0.1.7.dist-info/DESCRIPTION.rst
pvnhxgmgiq-0.1.7.dist-info/METADATA
pvnhxgmgiq-0.1.7.dist-info/RECORD
pvnhxgmgiq-0.1.7.dist-info/WHEEL
pvnhxgmgiq-0.1.7.dist-info/entry_points.txt
pvnhxgmgiq-0.1.7.dist-info/metadata.json
pvnhxgmgiq-0.1.7.dist-info/top_level.txt
